ignite/__init__.py
ignite/ignite.py
ignite-1.1.0.dist-info/DESCRIPTION.rst
ignite-1.1.0.dist-info/METADATA
ignite-1.1.0.dist-info/RECORD
ignite-1.1.0.dist-info/WHEEL
ignite-1.1.0.dist-info/metadata.json
ignite-1.1.0.dist-info/top_level.txt
